{"yyqxHMt2girkiB46hIH7jg==":"mbr-4.jpeg","Q3Iy98t36yM/pkqXwvrg8Q==":"background7.jpg","jds1NK+3HZIYOMgnWO+SRg==":"mbr-1920x1280.jpg","efIymbfSkX4G1GyrcMawqQ==":"gopr0001-2000x1500.jpg","KWb7Efv4m2/d8ngPNDo2sA==":"2021-08-26_20-23-32-2000x1125.jpg","S/bIzP+mwkRYmYupJwn18A==":"2021-08-26_17-48-31-2000x1125.jpg","9sbDzeiodjY+Fzv6+att1A==":"2021-08-26_20-23-17-2000x1125.jpg","CUfglrsUByWA4tO5NOWk1Q==":"2021-08-26_17-48-31-2000x1125.jpeg","tb/K6ySbfY1wZ8FUaoZjZA==":"img_20210815-125353-2000x1500.jpeg","On2CR2p/qr4g1Wo4BrXQgQ==":"img_20210815-125400-2000x1500.jpg","mizIhRYE6rYKcJRGFuRQRQ==":"mbr-1155x1920.png","oyGwYV8J2Ui2nLeopCbsRQ==":"mbr-1-1155x1920.png","NbpcvX1DE6GkmC0kjYIEJQ==":"mbr-1-1920x1280.jpg","wG5iViY9bA6gX+ZdFz/xyA==":"mbr-1256x837.jpg","Mh09G4eeVX1xDwB9mF7sxg==":"d24s6gw-89922562-9375-428d-a814-7c2678616a71-600x706.jpg","/BmTSdzVkUdk+vBs78iukA==":"kwuy2dfn-250x250.jpg","F0oUKiRdpe4lw6s8RYmV9w==":"mbr-3.jpeg","kAn50JTiQ/b8ZlXIwkFs9A==":"m-c-hard-662x406.jpg"}